scepter/__init__.py
scepter/version.py
scepter/methods/edit/dit_ace_0.6b_1024.yaml
scepter/methods/edit/dit_ace_0.6b_512.yaml
scepter/methods/edit/edit_512_lora.yaml
scepter/methods/examples/classification/example.yaml
scepter/methods/examples/generation/dit_cogvideox1.5_5b_i2v_lora.yaml
scepter/methods/examples/generation/dit_cogvideox1.5_5b_lora.yaml
scepter/methods/examples/generation/dit_cogvideox_2b_lora.yaml
scepter/methods/examples/generation/dit_cogvideox_5b_i2v_lora.yaml
scepter/methods/examples/generation/dit_cogvideox_5b_lora.yaml
scepter/methods/examples/generation/dit_flux1.0_dev_1024_lora.yaml
scepter/methods/examples/generation/dit_flux1.0_schnell_1024_lora.yaml
scepter/methods/examples/generation/dit_pixart_alpha_1024_lora.yaml
scepter/methods/examples/generation/dit_sd3_1024.yaml
scepter/methods/examples/generation/dit_sd3_1024_lora.yaml
scepter/methods/examples/generation/stable_diffusion_1.5_512.yaml
scepter/methods/examples/generation/stable_diffusion_1.5_512_lora.yaml
scepter/methods/examples/generation/stable_diffusion_1.5_512_textlora.yaml
scepter/methods/examples/generation/stable_diffusion_2.1_512.yaml
scepter/methods/examples/generation/stable_diffusion_2.1_512_lora.yaml
scepter/methods/examples/generation/stable_diffusion_2.1_768.yaml
scepter/methods/examples/generation/stable_diffusion_2.1_768_lora.yaml
scepter/methods/examples/generation/stable_diffusion_xl_1024.yaml
scepter/methods/examples/generation/stable_diffusion_xl_1024_lora.yaml
scepter/methods/examples/generation/stable_diffusion_xl_1024_textlora.yaml
scepter/methods/scedit/ctr/sd15_512_sce_ctr_hed.yaml
scepter/methods/scedit/ctr/sd21_768_sce_ctr_canny.yaml
scepter/methods/scedit/ctr/sd21_768_sce_ctr_pose.yaml
scepter/methods/scedit/ctr/sdxl_1024_sce_ctr_canny.yaml
scepter/methods/scedit/ctr/sdxl_1024_sce_ctr_color.yaml
scepter/methods/scedit/ctr/sdxl_1024_sce_ctr_color_datatxt.yaml
scepter/methods/scedit/ctr/sdxl_1024_sce_ctr_depth.yaml
scepter-1.4.1.dist-info/LICENSE
scepter-1.4.1.dist-info/METADATA
scepter-1.4.1.dist-info/WHEEL
scepter-1.4.1.dist-info/top_level.txt
scepter-1.4.1.dist-info/RECORD
