Metadata-Version: 2.1
Name: scepter
Version: 1.4.1
Home-page: 
Author: Tongyi Lab
Author-email: 
Keywords: compute vision,framework,generation,image edition.
Classifier: Programming Language :: Python :: 3.8
Classifier: Programming Language :: Python :: 3.9
Classifier: Programming Language :: Python :: 3.10
Classifier: Programming Language :: Python :: 3.11
Classifier: License :: OSI Approved :: Apache Software License
Classifier: Operating System :: OS Independent
License-File: LICENSE
Requires-Dist: albumentations
Requires-Dist: beautifulsoup4
Requires-Dist: einops
Requires-Dist: modelscope[framework]
Requires-Dist: ms-swift
Requires-Dist: numpy
Requires-Dist: open-clip-torch
Requires-Dist: opencv-python
Requires-Dist: opencv-transforms >=0.0.6
Requires-Dist: oss2 >=2.15.0
Requires-Dist: pycocotools
Requires-Dist: pyyaml >=5.3.1
Requires-Dist: scikit-image
Requires-Dist: scikit-learn
Requires-Dist: sentencepiece
Requires-Dist: torchsde
Requires-Dist: transformers
Requires-Dist: bitsandbytes
Requires-Dist: gradio
Requires-Dist: gradio-imageslider
Requires-Dist: imagehash
Requires-Dist: psutil
Requires-Dist: tiktoken
Requires-Dist: transformers-stream-generator
